<?xml version="1.0" encoding="UTF-8"?>

<!-- generated on 2024-07-17 09:27:11 by Eclipse SUMO netconvert Version 1.20.0
<configuration xmlns:xsi="http://www.w3.org/2001/XMLSchema-instance" xsi:noNamespaceSchemaLocation="http://sumo.dlr.de/xsd/netconvertConfiguration.xsd">

    <input>
        <type-files value="${SUMO_HOME}/data/typemap/osmNetconvert.typ.xml"/>
        <osm-files value="osm_bbox.osm.xml.gz"/>
    </input>

    <output>
        <output-file value="osm.net.xml.gz"/>
        <output.street-names value="true"/>
        <output.original-names value="true"/>
    </output>

    <projection>
        <proj value="+proj=merc +a=6378137 +b=6378137 +lat_ts=0.0 +lon_0=0.0 +x_0=0.0 +y_0=0 +k=1.0 +units=m +nadgrids=@null +wktext +no_defs"/>
    </projection>

    <processing>
        <geometry.remove value="true"/>
        <roundabouts.guess value="true"/>
    </processing>

    <tls_building>
        <tls.discard-simple value="true"/>
        <tls.join value="true"/>
        <tls.guess-signals value="true"/>
        <tls.default-type value="actuated"/>
    </tls_building>

    <ramp_guessing>
        <ramps.guess value="true"/>
    </ramp_guessing>

    <edge_removal>
        <keep-edges.by-vclass value="passenger"/>
    </edge_removal>

    <junctions>
        <junctions.join value="true"/>
        <junctions.corner-detail value="5"/>
    </junctions>

</configuration>
-->

<net version="1.20" junctionCornerDetail="5" limitTurnSpeed="5.50" xmlns:xsi="http://www.w3.org/2001/XMLSchema-instance" xsi:noNamespaceSchemaLocation="http://sumo.dlr.de/xsd/net_file.xsd">

    <location netOffset="-1287410.67,-6131405.43" convBoundary="0.00,0.00,506.82,528.25" origBoundary="11.565007,48.147339,11.569755,48.150555" projParameter="+proj=merc +a=6378137 +b=6378137 +lat_ts=0.0 +lon_0=0.0 +x_0=0.0 +y_0=0 +k=1.0 +units=m +nadgrids=@null +wktext +no_defs"/>

    <type id="highway.residential" priority="3" numLanes="1" speed="13.89" disallow="tram rail_urban rail rail_electric rail_fast ship container cable_car subway aircraft wheelchair scooter drone" oneway="0"/>
    <type id="highway.secondary" priority="11" numLanes="1" speed="27.78" disallow="tram rail_urban rail rail_electric rail_fast ship container cable_car subway aircraft wheelchair scooter drone" oneway="0"/>

    <edge id=":1680609182_0" function="internal">
        <lane id=":1680609182_0_0" index="0" disallow="pedestrian tram rail_urban rail rail_electric rail_fast ship container cable_car subway aircraft wheelchair scooter drone" speed="13.89" length="0.30" shape="163.04,428.92 162.92,428.64"/>
    </edge>
    <edge id=":1680609182_1" function="internal">
        <lane id=":1680609182_1_0" index="0" disallow="pedestrian tram rail_urban rail rail_electric rail_fast ship container cable_car subway aircraft wheelchair scooter drone" speed="13.89" length="0.29" shape="165.86,427.37 165.98,427.65"/>
    </edge>
    <edge id=":2064183917_0" function="internal">
        <lane id=":2064183917_0_0" index="0" disallow="pedestrian tram rail_urban rail rail_electric rail_fast ship container cable_car subway aircraft wheelchair scooter drone" speed="3.65" length="4.67" shape="315.88,0.62 316.15,-0.79 316.73,-1.47 317.62,-1.42 318.82,-0.62"/>
    </edge>
    <edge id=":21457468_0" function="internal">
        <lane id=":21457468_0_0" index="0" disallow="tram rail_urban rail rail_electric rail_fast ship container cable_car subway aircraft wheelchair scooter drone" speed="7.09" length="10.52" width="7.10" shape="117.70,324.62 116.08,321.83 114.19,320.13 112.02,319.51 109.58,319.97"/>
    </edge>
    <edge id=":21457468_1" function="internal">
        <lane id=":21457468_1_0" index="0" disallow="tram rail_urban rail rail_electric rail_fast ship container cable_car subway aircraft wheelchair scooter drone" speed="13.89" length="14.73" shape="117.70,324.62 111.80,311.13"/>
    </edge>
    <edge id=":21457468_2" function="internal">
        <lane id=":21457468_2_0" index="0" disallow="tram rail_urban rail rail_electric rail_fast ship container cable_car subway aircraft wheelchair scooter drone" speed="3.65" length="1.44" shape="117.70,324.62 117.95,323.20"/>
    </edge>
    <edge id=":21457468_6" function="internal">
        <lane id=":21457468_6_0" index="0" disallow="tram rail_urban rail rail_electric rail_fast ship container cable_car subway aircraft wheelchair scooter drone" speed="3.65" length="3.23" shape="117.95,323.20 118.52,322.51 119.41,322.55 120.63,323.32"/>
    </edge>
    <edge id=":21457468_3" function="internal">
        <lane id=":21457468_3_0" index="0" disallow="tram rail_urban rail rail_electric rail_fast ship container cable_car subway aircraft wheelchair scooter drone" speed="13.89" length="14.69" shape="114.74,309.87 120.63,323.32"/>
    </edge>
    <edge id=":21457468_4" function="internal">
        <lane id=":21457468_4_0" index="0" disallow="tram rail_urban rail rail_electric rail_fast ship container cable_car subway aircraft wheelchair scooter drone" speed="7.60" length="3.43" width="7.10" shape="114.74,309.87 115.53,313.09 115.51,313.20"/>
    </edge>
    <edge id=":21457468_5" function="internal">
        <lane id=":21457468_5_0" index="0" disallow="tram rail_urban rail rail_electric rail_fast ship container cable_car subway aircraft wheelchair scooter drone" speed="3.65" length="1.44" shape="114.74,309.87 114.48,311.29"/>
    </edge>
    <edge id=":21457468_7" function="internal">
        <lane id=":21457468_7_0" index="0" disallow="tram rail_urban rail rail_electric rail_fast ship container cable_car subway aircraft wheelchair scooter drone" speed="7.60" length="9.59" width="7.10" shape="115.51,313.20 114.94,315.85 112.95,318.15 109.58,319.97"/>
    </edge>
    <edge id=":21457468_8" function="internal">
        <lane id=":21457468_8_0" index="0" disallow="tram rail_urban rail rail_electric rail_fast ship container cable_car subway aircraft wheelchair scooter drone" speed="3.65" length="3.23" shape="114.48,311.29 113.90,311.97 113.01,311.92 111.80,311.13"/>
    </edge>
    <edge id=":2269137859_0" function="internal">
        <lane id=":2269137859_0_0" index="0" disallow="tram rail_urban rail rail_electric rail_fast ship container cable_car subway aircraft wheelchair scooter drone" speed="3.65" length="4.67" shape="19.12,96.34 19.40,94.93 19.98,94.26 20.88,94.32 22.07,95.12"/>
    </edge>
    <edge id=":29564155_0" function="internal">
        <lane id=":29564155_0_0" index="0" disallow="pedestrian tram rail_urban rail rail_electric rail_fast ship container cable_car subway aircraft wheelchair scooter drone" speed="13.89" length="14.41" shape="335.98,47.91 330.28,34.67"/>
    </edge>
    <edge id=":29564155_1" function="internal">
        <lane id=":29564155_1_0" index="0" disallow="tram rail_urban rail rail_electric rail_fast ship container cable_car subway aircraft wheelchair scooter drone" speed="7.27" length="2.64" shape="335.98,47.91 335.49,45.42 335.53,45.33"/>
    </edge>
    <edge id=":29564155_2" function="internal">
        <lane id=":29564155_2_0" index="0" disallow="tram rail_urban rail rail_electric rail_fast ship container cable_car subway aircraft wheelchair scooter drone" speed="3.65" length="1.44" shape="335.98,47.91 336.23,46.49"/>
    </edge>
    <edge id=":29564155_10" function="internal">
        <lane id=":29564155_10_0" index="0" disallow="tram rail_urban rail rail_electric rail_fast ship container cable_car subway aircraft wheelchair scooter drone" speed="7.27" length="9.09" shape="335.53,45.33 336.30,43.16 338.42,41.14 341.84,39.34"/>
    </edge>
    <edge id=":29564155_11" function="internal">
        <lane id=":29564155_11_0" index="0" disallow="tram rail_urban rail rail_electric rail_fast ship container cable_car subway aircraft wheelchair scooter drone" speed="3.65" length="3.23" shape="336.23,46.49 336.80,45.80 337.70,45.85 338.91,46.63"/>
    </edge>
    <edge id=":29564155_3" function="internal">
        <lane id=":29564155_3_0" index="0" disallow="pedestrian tram rail_urban rail rail_electric rail_fast ship container cable_car subway aircraft wheelchair scooter drone" speed="6.53" length="9.05" shape="333.23,33.42 334.50,35.53 336.16,36.72 338.19,37.01 340.61,36.38"/>
    </edge>
    <edge id=":29564155_4" function="internal">
        <lane id=":29564155_4_0" index="0" disallow="pedestrian tram rail_urban rail rail_electric rail_fast ship container cable_car subway aircraft wheelchair scooter drone" speed="13.89" length="14.37" shape="333.23,33.42 338.91,46.63"/>
    </edge>
    <edge id=":29564155_5" function="internal">
        <lane id=":29564155_5_0" index="0" disallow="pedestrian tram rail_urban rail rail_electric rail_fast ship container cable_car subway aircraft wheelchair scooter drone" speed="3.65" length="1.44" shape="333.23,33.42 332.96,34.84"/>
    </edge>
    <edge id=":29564155_12" function="internal">
        <lane id=":29564155_12_0" index="0" disallow="pedestrian tram rail_urban rail rail_electric rail_fast ship container cable_car subway aircraft wheelchair scooter drone" speed="3.65" length="3.23" shape="332.96,34.84 332.38,35.52 331.49,35.46 330.28,34.67"/>
    </edge>
    <edge id=":29564155_6" function="internal">
        <lane id=":29564155_6_0" index="0" disallow="pedestrian tram rail_urban rail rail_electric rail_fast ship container cable_car subway aircraft wheelchair scooter drone" speed="6.66" length="9.22" shape="327.29,42.26 329.42,40.87 330.63,39.15 330.91,37.08 330.28,34.67"/>
    </edge>
    <edge id=":29564155_7" function="internal">
        <lane id=":29564155_7_0" index="0" disallow="tram rail_urban rail rail_electric rail_fast ship container cable_car subway aircraft wheelchair scooter drone" speed="13.89" length="14.48" shape="327.29,42.26 340.61,36.38"/>
        <lane id=":29564155_7_1" index="1" disallow="tram rail_urban rail rail_electric rail_fast ship container cable_car subway aircraft wheelchair scooter drone" speed="13.89" length="14.48" shape="328.65,45.15 341.84,39.34"/>
    </edge>
    <edge id=":29564155_9" function="internal">
        <lane id=":29564155_9_0" index="0" disallow="tram rail_urban rail rail_electric rail_fast ship container cable_car subway aircraft wheelchair scooter drone" speed="7.26" length="11.72" shape="328.65,45.15 332.28,43.84 335.21,43.65 337.41,44.58 338.91,46.63"/>
    </edge>
    <edge id=":2959331869_0" function="internal">
        <lane id=":2959331869_0_0" index="0" disallow="tram rail_urban rail rail_electric rail_fast ship container cable_car subway aircraft wheelchair scooter drone" speed="13.89" length="8.21" shape="264.16,70.38 266.27,69.22 267.53,68.09 268.80,66.95 270.91,65.79"/>
        <lane id=":2959331869_0_1" index="1" disallow="tram rail_urban rail rail_electric rail_fast ship container cable_car subway aircraft wheelchair scooter drone" speed="13.89" length="8.21" shape="264.16,70.38 266.47,69.68 268.16,69.56 269.85,69.44 272.15,68.74"/>
    </edge>
    <edge id=":345553442_0" function="internal">
        <lane id=":345553442_0_0" index="0" disallow="pedestrian tram rail_urban rail rail_electric rail_fast ship container cable_car subway aircraft wheelchair scooter drone" speed="7.66" length="12.16" width="8.50" shape="200.08,517.60 198.28,514.41 196.10,512.51 193.56,511.89 190.65,512.55"/>
    </edge>
    <edge id=":345553442_1" function="internal">
        <lane id=":345553442_1_0" index="0" disallow="pedestrian tram rail_urban rail rail_electric rail_fast ship container cable_car subway aircraft wheelchair scooter drone" speed="11.11" length="16.62" shape="200.08,517.60 194.59,501.92"/>
    </edge>
    <edge id=":345553442_2" function="internal">
        <lane id=":345553442_2_0" index="0" disallow="tram rail_urban rail rail_electric rail_fast ship container cable_car subway aircraft wheelchair scooter drone" speed="4.76" length="3.21" width="5.45" shape="200.08,517.60 200.54,515.19 201.03,514.62"/>
    </edge>
    <edge id=":345553442_9" function="internal">
        <lane id=":345553442_9_0" index="0" disallow="tram rail_urban rail rail_electric rail_fast ship container cable_car subway aircraft wheelchair scooter drone" speed="4.76" length="4.75" width="5.45" shape="201.03,514.62 201.53,514.03 203.05,514.13 205.10,515.48"/>
    </edge>
    <edge id=":345553442_3" function="internal">
        <lane id=":345553442_3_0" index="0" disallow="pedestrian tram rail_urban rail rail_electric rail_fast ship container cable_car subway aircraft wheelchair scooter drone" speed="7.20" length="11.05" width="5.45" shape="209.70,506.95 206.79,508.55 205.05,510.51 204.49,512.82 205.10,515.48"/>
    </edge>
    <edge id=":345553442_4" function="internal">
        <lane id=":345553442_4_0" index="0" disallow="pedestrian tram rail_urban rail rail_electric rail_fast ship container cable_car subway aircraft wheelchair scooter drone" speed="13.89" length="19.88" width="8.50" shape="209.70,506.95 203.49,509.13 198.45,510.43 194.28,511.39 190.65,512.55"/>
    </edge>
    <edge id=":345553442_5" function="internal">
        <lane id=":345553442_5_0" index="0" disallow="pedestrian tram rail_urban rail rail_electric rail_fast ship container cable_car subway aircraft wheelchair scooter drone" speed="8.35" length="14.96" shape="208.09,503.01 203.10,504.64 199.18,505.00 196.35,504.09 194.59,501.92"/>
    </edge>
    <edge id=":345553442_6" function="internal">
        <lane id=":345553442_6_0" index="0" disallow="pedestrian tram rail_urban rail rail_electric rail_fast ship container cable_car subway aircraft wheelchair scooter drone" speed="11.11" length="16.79" width="5.45" shape="200.47,499.38 202.32,504.49 203.30,508.58 204.02,512.10 205.10,515.48"/>
    </edge>
    <edge id=":345553442_7" function="internal">
        <lane id=":345553442_7_0" index="0" disallow="pedestrian tram rail_urban rail rail_electric rail_fast ship container cable_car subway aircraft wheelchair scooter drone" speed="8.34" length="3.98" width="8.50" shape="197.53,500.65 198.34,504.25 198.26,504.53"/>
    </edge>
    <edge id=":345553442_8" function="internal">
        <lane id=":345553442_8_0" index="0" disallow="pedestrian tram rail_urban rail rail_electric rail_fast ship container cable_car subway aircraft wheelchair scooter drone" speed="3.65" length="1.44" shape="197.53,500.65 197.27,502.07"/>
    </edge>
    <edge id=":345553442_10" function="internal">
        <lane id=":345553442_10_0" index="0" disallow="pedestrian tram rail_urban rail rail_electric rail_fast ship container cable_car subway aircraft wheelchair scooter drone" speed="8.34" length="11.64" width="8.50" shape="198.26,504.53 197.46,507.43 194.89,510.20 190.65,512.55"/>
    </edge>
    <edge id=":345553442_11" function="internal">
        <lane id=":345553442_11_0" index="0" disallow="pedestrian tram rail_urban rail rail_electric rail_fast ship container cable_car subway aircraft wheelchair scooter drone" speed="3.65" length="3.23" shape="197.27,502.07 196.70,502.75 195.80,502.70 194.59,501.92"/>
    </edge>
    <edge id=":345553456_0" function="internal">
        <lane id=":345553456_0_0" index="0" disallow="tram rail_urban rail rail_electric rail_fast ship container cable_car subway aircraft wheelchair scooter drone" speed="13.89" length="11.26" shape="49.73,167.02 45.22,156.70"/>
    </edge>
    <edge id=":345553456_1" function="internal">
        <lane id=":345553456_1_0" index="0" disallow="tram rail_urban rail rail_electric rail_fast ship container cable_car subway aircraft wheelchair scooter drone" speed="7.31" length="2.52" shape="49.73,167.02 49.26,164.54"/>
    </edge>
    <edge id=":345553456_2" function="internal">
        <lane id=":345553456_2_0" index="0" disallow="tram rail_urban rail rail_electric rail_fast ship container cable_car subway aircraft wheelchair scooter drone" speed="3.65" length="1.44" shape="49.73,167.02 49.99,165.60"/>
    </edge>
    <edge id=":345553456_9" function="internal">
        <lane id=":345553456_9_0" index="0" disallow="tram rail_urban rail rail_electric rail_fast ship container cable_car subway aircraft wheelchair scooter drone" speed="7.31" length="9.22" shape="49.26,164.54 50.08,162.28 52.21,160.24 55.62,158.43"/>
    </edge>
    <edge id=":345553456_10" function="internal">
        <lane id=":345553456_10_0" index="0" disallow="tram rail_urban rail rail_electric rail_fast ship container cable_car subway aircraft wheelchair scooter drone" speed="3.65" length="3.23" shape="49.99,165.60 50.56,164.92 51.46,164.97 52.67,165.76"/>
    </edge>
    <edge id=":345553456_3" function="internal">
        <lane id=":345553456_3_0" index="0" disallow="tram rail_urban rail rail_electric rail_fast ship container cable_car subway aircraft wheelchair scooter drone" speed="6.59" length="9.15" shape="48.15,155.41 49.48,157.55 51.17,158.76 53.21,159.05 55.62,158.43"/>
    </edge>
    <edge id=":345553456_4" function="internal">
        <lane id=":345553456_4_0" index="0" disallow="tram rail_urban rail rail_electric rail_fast ship container cable_car subway aircraft wheelchair scooter drone" speed="13.89" length="11.29" shape="48.15,155.41 52.67,165.76"/>
    </edge>
    <edge id=":345553456_5" function="internal">
        <lane id=":345553456_5_0" index="0" disallow="tram rail_urban rail rail_electric rail_fast ship container cable_car subway aircraft wheelchair scooter drone" speed="3.65" length="1.44" shape="48.15,155.41 47.91,156.83"/>
    </edge>
    <edge id=":345553456_11" function="internal">
        <lane id=":345553456_11_0" index="0" disallow="tram rail_urban rail rail_electric rail_fast ship container cable_car subway aircraft wheelchair scooter drone" speed="3.65" length="3.23" shape="47.91,156.83 47.33,157.52 46.44,157.48 45.22,156.70"/>
    </edge>
    <edge id=":345553456_6" function="internal">
        <lane id=":345553456_6_0" index="0" disallow="tram rail_urban rail rail_electric rail_fast ship container cable_car subway aircraft wheelchair scooter drone" speed="6.48" length="9.03" shape="42.32,164.05 44.44,162.76 45.64,161.11 45.90,159.09 45.22,156.70"/>
    </edge>
    <edge id=":345553456_7" function="internal">
        <lane id=":345553456_7_0" index="0" disallow="tram rail_urban rail rail_electric rail_fast ship container cable_car subway aircraft wheelchair scooter drone" speed="13.89" length="14.44" shape="42.32,164.05 55.62,158.43"/>
    </edge>
    <edge id=":345553456_8" function="internal">
        <lane id=":345553456_8_0" index="0" disallow="tram rail_urban rail rail_electric rail_fast ship container cable_car subway aircraft wheelchair scooter drone" speed="7.35" length="11.78" shape="42.32,164.05 46.01,162.86 48.97,162.75 51.19,163.71 52.67,165.76"/>
    </edge>
    <edge id=":618163560_0" function="internal">
        <lane id=":618163560_0_0" index="0" disallow="pedestrian tram rail_urban rail rail_electric rail_fast ship container cable_car subway aircraft wheelchair scooter drone" speed="13.89" length="3.05" width="4.25" shape="290.07,473.38 289.28,473.82 288.80,474.23 288.31,474.64 287.52,475.07"/>
        <lane id=":618163560_0_1" index="1" disallow="pedestrian tram rail_urban rail rail_electric rail_fast ship container cable_car subway aircraft wheelchair scooter drone" speed="13.89" length="3.05" width="4.25" shape="288.76,470.45 287.92,470.74 287.30,470.82 286.68,470.89 285.84,471.16"/>
    </edge>
    <edge id=":618697472_0" function="internal">
        <lane id=":618697472_0_0" index="0" disallow="pedestrian tram rail_urban rail rail_electric rail_fast ship container cable_car subway aircraft wheelchair scooter drone" speed="3.65" length="4.67" shape="495.35,410.96 495.11,412.38 494.54,413.07 493.65,413.03 492.43,412.26"/>
    </edge>
    <edge id=":8736309647_0" function="internal">
        <lane id=":8736309647_0_0" index="0" disallow="pedestrian tram rail_urban rail rail_electric rail_fast ship container cable_car subway aircraft wheelchair scooter drone" speed="13.89" length="8.00" shape="180.66,469.66 177.48,462.31"/>
    </edge>
    <edge id=":8736309647_1" function="internal">
        <lane id=":8736309647_1_0" index="0" disallow="pedestrian tram rail_urban rail rail_electric rail_fast ship container cable_car subway aircraft wheelchair scooter drone" speed="13.89" length="8.40" shape="180.42,461.04 181.86,463.11 183.48,464.08 185.10,465.06 186.53,467.12"/>
        <lane id=":8736309647_1_1" index="1" disallow="pedestrian tram rail_urban rail rail_electric rail_fast ship container cable_car subway aircraft wheelchair scooter drone" speed="13.89" length="8.40" shape="180.42,461.04 183.59,468.39"/>
    </edge>
    <edge id=":8748896839_0" function="internal">
        <lane id=":8748896839_0_0" index="0" disallow="tram rail_urban rail rail_electric rail_fast ship container cable_car subway aircraft wheelchair scooter drone" speed="4.76" length="7.96" width="5.45" shape="205.79,517.11 205.33,519.53 204.34,520.69 202.82,520.59 200.77,519.24"/>
    </edge>
    <edge id=":967091764_0" function="internal">
        <lane id=":967091764_0_0" index="0" disallow="pedestrian tram rail_urban rail rail_electric rail_fast ship container cable_car subway aircraft wheelchair scooter drone" speed="6.55" length="9.05" shape="485.04,395.68 483.73,393.59 482.06,392.40 480.03,392.13 477.63,392.76"/>
    </edge>
    <edge id=":967091764_1" function="internal">
        <lane id=":967091764_1_0" index="0" disallow="pedestrian tram rail_urban rail rail_electric rail_fast ship container cable_car subway aircraft wheelchair scooter drone" speed="13.89" length="14.36" shape="485.04,395.68 479.40,382.48"/>
    </edge>
    <edge id=":967091764_2" function="internal">
        <lane id=":967091764_2_0" index="0" disallow="pedestrian tram rail_urban rail rail_electric rail_fast ship container cable_car subway aircraft wheelchair scooter drone" speed="3.65" length="1.44" shape="485.04,395.68 485.29,394.26"/>
    </edge>
    <edge id=":967091764_10" function="internal">
        <lane id=":967091764_10_0" index="0" disallow="pedestrian tram rail_urban rail rail_electric rail_fast ship container cable_car subway aircraft wheelchair scooter drone" speed="3.65" length="3.23" shape="485.29,394.26 485.86,393.57 486.75,393.61 487.97,394.39"/>
    </edge>
    <edge id=":967091764_3" function="internal">
        <lane id=":967091764_3_0" index="0" disallow="pedestrian tram rail_urban rail rail_electric rail_fast ship container cable_car subway aircraft wheelchair scooter drone" speed="6.85" length="10.25" shape="490.28,385.70 488.19,387.06 487.11,388.96 487.03,391.40 487.97,394.39"/>
    </edge>
    <edge id=":967091764_4" function="internal">
        <lane id=":967091764_4_0" index="0" disallow="tram rail_urban rail rail_electric rail_fast ship container cable_car subway aircraft wheelchair scooter drone" speed="13.89" length="14.51" shape="490.28,385.70 487.30,387.22 484.73,388.90 481.77,390.74 477.63,392.76"/>
        <lane id=":967091764_4_1" index="1" disallow="tram rail_urban rail rail_electric rail_fast ship container cable_car subway aircraft wheelchair scooter drone" speed="13.89" length="14.51" shape="490.28,385.70 487.10,386.76 484.11,387.43 480.72,388.25 476.38,389.81"/>
    </edge>
    <edge id=":967091764_6" function="internal">
        <lane id=":967091764_6_0" index="0" disallow="tram rail_urban rail rail_electric rail_fast ship container cable_car subway aircraft wheelchair scooter drone" speed="7.64" length="12.92" shape="490.28,385.70 486.55,386.78 483.49,386.60 481.11,385.17 479.40,382.48"/>
    </edge>
    <edge id=":967091764_7" function="internal">
        <lane id=":967091764_7_0" index="0" disallow="pedestrian tram rail_urban rail rail_electric rail_fast ship container cable_car subway aircraft wheelchair scooter drone" speed="13.89" length="14.28" shape="482.36,381.26 487.97,394.39"/>
    </edge>
    <edge id=":967091764_8" function="internal">
        <lane id=":967091764_8_0" index="0" disallow="tram rail_urban rail rail_electric rail_fast ship container cable_car subway aircraft wheelchair scooter drone" speed="7.34" length="2.50" shape="482.36,381.26 482.78,383.72"/>
    </edge>
    <edge id=":967091764_9" function="internal">
        <lane id=":967091764_9_0" index="0" disallow="tram rail_urban rail rail_electric rail_fast ship container cable_car subway aircraft wheelchair scooter drone" speed="3.65" length="1.44" shape="482.36,381.26 482.08,382.67"/>
    </edge>
    <edge id=":967091764_11" function="internal">
        <lane id=":967091764_11_0" index="0" disallow="tram rail_urban rail rail_electric rail_fast ship container cable_car subway aircraft wheelchair scooter drone" speed="7.34" length="9.21" shape="482.78,383.72 481.93,385.97 479.79,388.00 476.38,389.81"/>
    </edge>
    <edge id=":967091764_12" function="internal">
        <lane id=":967091764_12_0" index="0" disallow="tram rail_urban rail rail_electric rail_fast ship container cable_car subway aircraft wheelchair scooter drone" speed="3.65" length="3.23" shape="482.08,382.67 481.49,383.35 480.60,383.28 479.40,382.48"/>
    </edge>

    <edge id="-27222779#2" from="345553456" to="2269137859" name="Luisenstraße" priority="3" type="highway.residential" shape="48.97,161.22 43.08,147.89 25.04,106.50 20.59,95.73">
        <lane id="-27222779#2_0" index="0" disallow="tram rail_urban rail rail_electric rail_fast ship container cable_car subway aircraft wheelchair scooter drone" speed="13.89" length="65.77" shape="45.22,156.70 41.62,148.53 23.56,107.12 19.12,96.34">
            <param key="origId" value="27222779"/>
        </lane>
    </edge>
    <edge id="-344664988#1" from="29564155" to="2064183917" name="Arcisstraße" priority="11" type="highway.secondary" shape="334.54,40.63 330.57,31.25 317.35,0.00">
        <lane id="-344664988#1_0" index="0" disallow="pedestrian tram rail_urban rail rail_electric rail_fast ship container cable_car subway aircraft wheelchair scooter drone" speed="13.89" length="36.97" shape="330.28,34.67 329.10,31.87 315.88,0.62">
            <param key="origId" value="344664988"/>
        </lane>
    </edge>
    <edge id="-392103887" from="8736309647" to="1680609182" name="Luisenstraße" priority="3" type="highway.residential">
        <lane id="-392103887_0" index="0" disallow="pedestrian tram rail_urban rail rail_electric rail_fast ship container cable_car subway aircraft wheelchair scooter drone" speed="13.89" length="36.39" shape="177.48,462.31 163.04,428.92">
            <param key="origId" value="392103887"/>
        </lane>
    </edge>
    <edge id="-40317921" from="8748896839" to="345553442" name="Luisenstraße" priority="3" type="highway.residential">
        <lane id="-40317921_0" index="0" disallow="tram rail_urban rail rail_electric rail_fast ship container cable_car subway aircraft wheelchair scooter drone" speed="8.33" length="1.77" width="5.45" shape="200.77,519.24 200.08,517.60">
            <param key="origId" value="40317921"/>
        </lane>
    </edge>
    <edge id="-40317922#2" from="21457468" to="345553456" name="Luisenstraße" priority="3" type="highway.residential" shape="116.23,317.37 90.29,257.16 53.76,172.33 48.97,161.22">
        <lane id="-40317922#2_0" index="0" disallow="tram rail_urban rail rail_electric rail_fast ship container cable_car subway aircraft wheelchair scooter drone" speed="13.89" length="156.91" shape="111.80,311.13 88.82,257.79 52.29,172.97 49.73,167.02">
            <param key="origId" value="40317922"/>
        </lane>
    </edge>
    <edge id="-40317922#4" from="1680609182" to="21457468" name="Luisenstraße" priority="3" type="highway.residential" shape="164.45,428.14 136.82,363.66 116.23,317.37">
        <lane id="-40317922#4_0" index="0" disallow="tram rail_urban rail rail_electric rail_fast ship container cable_car subway aircraft wheelchair scooter drone" speed="13.89" length="113.42" shape="162.92,428.64 135.36,364.30 117.70,324.62">
            <param key="origId" value="40317922"/>
        </lane>
    </edge>
    <edge id="-51476080#7" from="967091764" to="29564155" name="Arcisstraße" priority="11" type="highway.secondary" shape="483.62,388.50 479.66,378.91 473.60,364.17 436.80,279.01 429.33,261.78 421.69,243.96 409.07,214.51 380.80,148.46 345.68,66.10 340.37,53.96 339.28,51.45 334.54,40.63">
        <lane id="-51476080#7_0" index="0" disallow="tram rail_urban rail rail_electric rail_fast ship container cable_car subway aircraft wheelchair scooter drone" speed="13.89" length="364.02" shape="479.40,382.48 478.19,379.51 472.12,364.79 435.33,279.65 427.86,262.41 420.22,244.59 407.59,215.14 379.33,149.09 344.21,66.74 338.90,54.60 337.81,52.10 335.98,47.91">
            <param key="origId" value="51476080"/>
        </lane>
    </edge>
    <edge id="-51508352#1" from="618697472" to="967091764" name="Arcisstraße" priority="11" type="highway.secondary" shape="493.89,411.61 488.06,398.54 483.62,388.50">
        <lane id="-51508352#1_0" index="0" disallow="pedestrian tram rail_urban rail rail_electric rail_fast ship container cable_car subway aircraft wheelchair scooter drone" speed="13.89" length="18.15" shape="492.43,412.26 486.60,399.19 485.04,395.68">
            <param key="origId" value="51508352"/>
        </lane>
    </edge>
    <edge id="-943542797#1" from="345553442" to="8736309647" name="Luisenstraße" priority="3" type="highway.residential" shape="199.35,508.88 195.71,500.47 180.54,465.35">
        <lane id="-943542797#1_0" index="0" disallow="pedestrian tram rail_urban rail rail_electric rail_fast ship container cable_car subway aircraft wheelchair scooter drone" speed="13.89" length="35.14" shape="194.59,501.92 194.24,501.11 180.66,469.66">
            <param key="origId" value="943542797"/>
        </lane>
    </edge>
    <edge id="134941607#0" from="9094806366" to="345553456" name="Gabelsbergerstraße" priority="11" type="highway.secondary" spreadType="center" shape="0.00,182.06 38.61,165.63 48.97,161.22">
        <lane id="134941607#0_0" index="0" disallow="tram rail_urban rail rail_electric rail_fast ship container cable_car subway aircraft wheelchair scooter drone" speed="13.89" length="46.00" shape="-0.00,182.06 38.61,165.63 42.32,164.05">
            <param key="origId" value="134941607"/>
        </lane>
    </edge>
    <edge id="147557400#0" from="345553442" to="2836367319" name="Theresienstraße" priority="11" type="highway.secondary" spreadType="center" shape="199.35,508.88 189.78,512.92 162.15,524.53 153.31,528.25">
        <lane id="147557400#0_0" index="0" disallow="pedestrian tram rail_urban rail rail_electric rail_fast ship container cable_car subway aircraft wheelchair scooter drone" speed="13.89" length="40.50" width="8.50" shape="190.65,512.55 189.78,512.92 162.15,524.53 153.31,528.25">
            <param key="origId" value="147557400"/>
        </lane>
    </edge>
    <edge id="149935566#0" from="967091764" to="618163560" name="Theresienstraße" priority="11" type="highway.secondary" spreadType="center" shape="483.62,388.50 474.87,392.19 461.33,397.91 438.64,407.50 417.29,416.53 408.26,420.32 393.25,426.82 359.88,440.96 302.19,466.22 288.05,472.52">
        <lane id="149935566#0_0" index="0" disallow="tram rail_urban rail rail_electric rail_fast ship container cable_car subway aircraft wheelchair scooter drone" speed="13.89" length="204.19" shape="477.63,392.76 475.49,393.66 461.95,399.38 439.27,408.98 417.91,418.00 408.89,421.79 393.88,428.30 360.52,442.43 302.83,467.68 290.07,473.38">
            <param key="origId" value="149935566 149935566 58561798 58561800 58561800 58561801"/>
        </lane>
        <lane id="149935566#0_1" index="1" disallow="tram rail_urban rail rail_electric rail_fast ship container cable_car subway aircraft wheelchair scooter drone" speed="13.89" length="204.19" shape="476.38,389.81 474.24,390.71 460.71,396.44 438.02,406.03 416.67,415.06 407.64,418.85 392.62,425.35 359.25,439.49 301.54,464.75 288.76,470.45">
            <param key="origId" value="149935566 149935566 58561798 58561800 58561800 58561801"/>
        </lane>
    </edge>
    <edge id="27222779#0" from="2269137859" to="345553456" name="Luisenstraße" priority="3" type="highway.residential" shape="20.59,95.73 25.04,106.50 43.08,147.89 48.97,161.22">
        <lane id="27222779#0_0" index="0" disallow="tram rail_urban rail rail_electric rail_fast ship container cable_car subway aircraft wheelchair scooter drone" speed="13.89" length="65.69" shape="22.07,95.12 26.51,105.87 44.55,147.25 48.15,155.41">
            <param key="origId" value="27222779"/>
        </lane>
    </edge>
    <edge id="344664988#0" from="2064183917" to="29564155" name="Arcisstraße" priority="11" type="highway.secondary" shape="317.35,0.00 330.57,31.25 334.54,40.63">
        <lane id="344664988#0_0" index="0" disallow="pedestrian tram rail_urban rail rail_electric rail_fast ship container cable_car subway aircraft wheelchair scooter drone" speed="13.89" length="36.97" shape="318.82,-0.62 332.05,30.63 333.23,33.42">
            <param key="origId" value="344664988"/>
        </lane>
    </edge>
    <edge id="362368395#0" from="29564155" to="8748721381" name="Gabelsbergerstraße" priority="11" type="highway.secondary" spreadType="center" shape="334.54,40.63 343.99,36.72 350.33,34.04 401.43,12.26">
        <lane id="362368395#0_0" index="0" disallow="tram rail_urban rail rail_electric rail_fast ship container cable_car subway aircraft wheelchair scooter drone" speed="13.89" length="65.42" shape="340.61,36.38 343.37,35.25 349.71,32.56 400.80,10.79">
            <param key="origId" value="362368395"/>
        </lane>
        <lane id="362368395#0_1" index="1" disallow="tram rail_urban rail rail_electric rail_fast ship container cable_car subway aircraft wheelchair scooter drone" speed="13.89" length="65.42" shape="341.84,39.34 344.60,38.20 350.96,35.51 402.06,13.73">
            <param key="origId" value="362368395"/>
        </lane>
    </edge>
    <edge id="376401312#0" from="8748721326" to="967091764" name="Theresienstraße" priority="11" type="highway.secondary" spreadType="center" shape="506.82,378.74 498.73,382.14 483.62,388.50">
        <lane id="376401312#0_0" index="0" disallow="tram rail_urban rail rail_electric rail_fast ship container cable_car subway aircraft wheelchair scooter drone" speed="13.89" length="17.94" shape="506.82,378.74 498.73,382.14 490.28,385.70">
            <param key="origId" value="376401312"/>
        </lane>
    </edge>
    <edge id="392103887" from="1680609182" to="8736309647" name="Luisenstraße" priority="3" type="highway.residential">
        <lane id="392103887_0" index="0" disallow="pedestrian tram rail_urban rail rail_electric rail_fast ship container cable_car subway aircraft wheelchair scooter drone" speed="13.89" length="36.39" shape="165.98,427.65 180.42,461.04">
            <param key="origId" value="392103887"/>
        </lane>
    </edge>
    <edge id="40317921" from="345553442" to="8748896839" name="Luisenstraße" priority="3" type="highway.residential">
        <lane id="40317921_0" index="0" disallow="tram rail_urban rail rail_electric rail_fast ship container cable_car subway aircraft wheelchair scooter drone" speed="8.33" length="1.77" width="5.45" shape="205.10,515.48 205.79,517.11">
            <param key="origId" value="40317921"/>
        </lane>
    </edge>
    <edge id="40317922#0" from="345553456" to="21457468" name="Luisenstraße" priority="3" type="highway.residential" shape="48.97,161.22 53.76,172.33 90.29,257.16 116.23,317.37">
        <lane id="40317922#0_0" index="0" disallow="tram rail_urban rail rail_electric rail_fast ship container cable_car subway aircraft wheelchair scooter drone" speed="13.89" length="156.91" shape="52.67,165.76 55.23,171.70 91.76,256.52 114.74,309.87">
            <param key="origId" value="40317922"/>
        </lane>
    </edge>
    <edge id="40317922#3" from="21457468" to="1680609182" name="Luisenstraße" priority="3" type="highway.residential" shape="116.23,317.37 136.82,363.66 164.45,428.14">
        <lane id="40317922#3_0" index="0" disallow="tram rail_urban rail rail_electric rail_fast ship container cable_car subway aircraft wheelchair scooter drone" speed="13.89" length="113.46" shape="120.63,323.32 138.29,363.02 165.86,427.37">
            <param key="origId" value="40317922"/>
        </lane>
    </edge>
    <edge id="40317927#0" from="345553456" to="2959331869" name="Gabelsbergerstraße" priority="11" type="highway.secondary" spreadType="center" shape="48.97,161.22 60.09,156.55 132.95,125.87 165.45,112.13 210.23,93.18 247.15,77.58 267.85,68.82">
        <lane id="40317927#0_0" index="0" disallow="tram rail_urban rail rail_electric rail_fast ship container cable_car subway aircraft wheelchair scooter drone" speed="13.89" length="226.37" shape="55.62,158.43 60.09,156.55 132.95,125.87 165.45,112.13 210.23,93.18 247.15,77.58 264.16,70.38">
            <param key="origId" value="40317927 40317927 943540703 943540703"/>
        </lane>
    </edge>
    <edge id="4645392#0" from="21457468" to="9201837231" name="Steinheilstraße" priority="3" type="highway.residential" spreadType="center" shape="116.23,317.37 107.09,320.94 31.58,353.14 23.97,356.40">
        <lane id="4645392#0_0" index="0" disallow="tram rail_urban rail rail_electric rail_fast ship container cable_car subway aircraft wheelchair scooter drone" speed="13.89" length="93.04" width="7.10" shape="109.58,319.97 107.09,320.94 31.58,353.14 23.97,356.40">
            <param key="origId" value="4645392"/>
        </lane>
    </edge>
    <edge id="51476080#0" from="29564155" to="967091764" name="Arcisstraße" priority="11" type="highway.secondary" shape="334.54,40.63 339.28,51.45 340.37,53.96 345.68,66.10 380.80,148.46 409.07,214.51 421.69,243.96 429.33,261.78 436.80,279.01 473.60,364.17 479.66,378.91 483.62,388.50">
        <lane id="51476080#0_0" index="0" disallow="tram rail_urban rail rail_electric rail_fast ship container cable_car subway aircraft wheelchair scooter drone" speed="13.89" length="364.09" shape="338.91,46.63 340.75,50.81 341.84,53.32 347.15,65.47 382.27,147.83 410.54,213.88 423.16,243.33 430.80,261.15 438.26,278.38 475.07,363.55 481.14,378.30 482.36,381.26">
            <param key="origId" value="51476080"/>
        </lane>
    </edge>
    <edge id="51508352#0" from="967091764" to="618697472" name="Arcisstraße" priority="11" type="highway.secondary" shape="483.62,388.50 488.06,398.54 493.89,411.61">
        <lane id="51508352#0_0" index="0" disallow="pedestrian tram rail_urban rail rail_electric rail_fast ship container cable_car subway aircraft wheelchair scooter drone" speed="13.89" length="18.14" shape="487.97,394.39 489.52,397.89 495.35,410.96">
            <param key="origId" value="51508352"/>
        </lane>
    </edge>
    <edge id="58561799#0" from="618163560" to="345553442" name="Theresienstraße" priority="11" type="highway.secondary" spreadType="center" shape="288.05,472.52 283.01,474.69 208.90,504.98 199.35,508.88">
        <lane id="58561799#0_0" index="0" disallow="pedestrian tram rail_urban rail rail_electric rail_fast ship container cable_car subway aircraft wheelchair scooter drone" speed="13.89" length="84.05" width="4.25" shape="287.52,475.07 283.83,476.65 209.70,506.95">
            <param key="origId" value="58561799"/>
        </lane>
        <lane id="58561799#0_1" index="1" disallow="pedestrian tram rail_urban rail rail_electric rail_fast ship container cable_car subway aircraft wheelchair scooter drone" speed="13.89" length="84.05" width="4.25" shape="285.84,471.16 282.19,472.73 208.09,503.01">
            <param key="origId" value="58561799"/>
        </lane>
    </edge>
    <edge id="943540702#0" from="2959331869" to="29564155" name="Gabelsbergerstraße" priority="11" type="highway.secondary" spreadType="center" shape="267.85,68.82 294.28,57.64 326.21,44.53 334.54,40.63">
        <lane id="943540702#0_0" index="0" disallow="tram rail_urban rail rail_electric rail_fast ship container cable_car subway aircraft wheelchair scooter drone" speed="13.89" length="61.17" shape="270.91,65.79 293.67,56.17 325.57,43.06 327.29,42.26">
            <param key="origId" value="943540702"/>
        </lane>
        <lane id="943540702#0_1" index="1" disallow="tram rail_urban rail rail_electric rail_fast ship container cable_car subway aircraft wheelchair scooter drone" speed="13.89" length="61.17" shape="272.15,68.74 294.90,59.12 326.85,46.00 328.65,45.15">
            <param key="origId" value="943540702"/>
        </lane>
    </edge>
    <edge id="943542797#0" from="8736309647" to="345553442" name="Luisenstraße" priority="3" type="highway.residential" shape="180.54,465.35 195.71,500.47 199.35,508.88">
        <lane id="943542797#0_0" index="0" disallow="pedestrian tram rail_urban rail rail_electric rail_fast ship container cable_car subway aircraft wheelchair scooter drone" speed="13.89" length="35.14" shape="186.53,467.12 200.12,498.57 200.47,499.38">
            <param key="origId" value="943542797"/>
        </lane>
        <lane id="943542797#0_1" index="1" disallow="pedestrian tram rail_urban rail rail_electric rail_fast ship container cable_car subway aircraft wheelchair scooter drone" speed="13.89" length="35.14" shape="183.59,468.39 197.18,499.84 197.53,500.65">
            <param key="origId" value="943542797"/>
        </lane>
    </edge>

    <tlLogic id="29564155" type="actuated" programID="0" offset="0">
        <phase duration="42" state="GggGGgrrrr" minDur="5" maxDur="50"/>
        <phase duration="3"  state="yyyyyyrrrr"/>
        <phase duration="42" state="rrrrrrGGGG" minDur="5" maxDur="50"/>
        <phase duration="3"  state="rrrrrryyyy"/>
    </tlLogic>
    <tlLogic id="345553442" type="actuated" programID="0" offset="0">
        <phase duration="38" state="GGgrrrGgg" minDur="5" maxDur="50"/>
        <phase duration="3"  state="yyyrrrGgg"/>
        <phase duration="6"  state="rrrrrrGGG" minDur="5" maxDur="50"/>
        <phase duration="3"  state="rrrrrryyy"/>
        <phase duration="37" state="rrrGGGrrr" minDur="5" maxDur="50"/>
        <phase duration="3"  state="rrryyyrrr"/>
    </tlLogic>
    <tlLogic id="345553456" type="actuated" programID="0" offset="0">
        <phase duration="42" state="GggGGgrrr" minDur="5" maxDur="50"/>
        <phase duration="3"  state="yyyyyyrrr"/>
        <phase duration="42" state="rrrrrrGGG" minDur="5" maxDur="50"/>
        <phase duration="3"  state="rrrrrryyy"/>
    </tlLogic>
    <tlLogic id="967091764" type="actuated" programID="0" offset="0">
        <phase duration="42" state="GGgrrrrGgg" minDur="5" maxDur="50"/>
        <phase duration="3"  state="yyyrrrryyy"/>
        <phase duration="42" state="rrrGGGGrrr" minDur="5" maxDur="50"/>
        <phase duration="3"  state="rrryyyyrrr"/>
    </tlLogic>

    <junction id="1680609182" type="priority" x="164.45" y="428.14" incLanes="-392103887_0 40317922#3_0" intLanes=":1680609182_0_0 :1680609182_1_0" shape="161.57,429.55 167.45,427.01 167.33,426.74 161.45,429.27">
        <request index="0" response="00" foes="00" cont="0"/>
        <request index="1" response="00" foes="00" cont="0"/>
    </junction>
    <junction id="2064183917" type="priority" x="317.35" y="0.00" incLanes="-344664988#1_0" intLanes=":2064183917_0_0" shape="317.35,-0.00 314.40,1.25 317.35,0.00">
        <request index="0" response="0" foes="0" cont="0"/>
    </junction>
    <junction id="21457468" type="priority" x="116.23" y="317.37" incLanes="-40317922#4_0 40317922#0_0" intLanes=":21457468_0_0 :21457468_1_0 :21457468_6_0 :21457468_3_0 :21457468_7_0 :21457468_8_0" shape="116.24,325.27 122.09,322.67 116.21,309.23 110.33,311.77 110.77,313.87 110.57,314.75 110.09,315.50 109.33,316.14 108.28,316.66 110.87,323.28 113.16,322.84 114.12,323.03 114.95,323.50 115.66,324.25">
        <request index="0" response="000000" foes="010000" cont="0"/>
        <request index="1" response="000000" foes="110000" cont="0"/>
        <request index="2" response="001000" foes="001000" cont="1"/>
        <request index="3" response="000000" foes="000100" cont="0"/>
        <request index="4" response="000011" foes="000011" cont="1"/>
        <request index="5" response="000010" foes="000010" cont="1"/>
    </junction>
    <junction id="2269137859" type="priority" x="20.59" y="95.73" incLanes="-27222779#2_0" intLanes=":2269137859_0_0" shape="20.59,95.73 17.64,96.96 20.59,95.73">
        <request index="0" response="0" foes="0" cont="0"/>
    </junction>
    <junction id="2836367319" type="dead_end" x="153.31" y="528.25" incLanes="147557400#0_0" intLanes="" shape="154.96,532.17 151.66,524.34"/>
    <junction id="29564155" type="traffic_light" x="334.54" y="40.63" incLanes="-51476080#7_0 344664988#0_0 943540702#0_0 943540702#0_1" intLanes=":29564155_0_0 :29564155_10_0 :29564155_11_0 :29564155_3_0 :29564155_4_0 :29564155_12_0 :29564155_6_0 :29564155_7_0 :29564155_7_1 :29564155_9_0" shape="334.51,48.55 340.38,45.98 339.90,43.79 340.10,42.87 340.59,42.07 341.37,41.39 342.45,40.82 340.00,34.91 337.75,35.36 336.80,35.16 335.98,34.66 335.28,33.88 334.70,32.80 328.81,35.29 329.27,37.57 329.05,38.54 328.54,39.41 327.72,40.16 326.61,40.81 329.33,46.60 331.50,46.07 332.42,46.25 333.23,46.72 333.93,47.49">
        <request index="0" response="1111000000" foes="1111100000" cont="0"/>
        <request index="1" response="1110010000" foes="1110010000" cont="1"/>
        <request index="2" response="1000010000" foes="1000010000" cont="1"/>
        <request index="3" response="0110000000" foes="0110000000" cont="0"/>
        <request index="4" response="1110000000" foes="1110000110" cont="0"/>
        <request index="5" response="0001000001" foes="0001000001" cont="1"/>
        <request index="6" response="0000000000" foes="0000100001" cont="0"/>
        <request index="7" response="0000000010" foes="0000011011" cont="0"/>
        <request index="8" response="0000000010" foes="0000011011" cont="0"/>
        <request index="9" response="0000000010" foes="0000010111" cont="0"/>
    </junction>
    <junction id="2959331869" type="priority" x="267.85" y="68.82" incLanes="40317927#0_0" intLanes=":2959331869_0_0 :2959331869_0_1" shape="272.78,70.21 270.28,64.32 267.70,65.86 266.12,67.36 265.08,68.13 263.54,68.91 264.79,71.85 267.69,71.08 269.87,70.99 271.14,70.77">
        <request index="0" response="00" foes="00" cont="0"/>
        <request index="1" response="00" foes="00" cont="0"/>
    </junction>
    <junction id="345553442" type="traffic_light" x="199.35" y="508.88" incLanes="-40317921_0 58561799#0_0 58561799#0_1 943542797#0_0 943542797#0_1" intLanes=":345553442_0_0 :345553442_1_0 :345553442_9_0 :345553442_3_0 :345553442_4_0 :345553442_5_0 :345553442_6_0 :345553442_10_0 :345553442_11_0" shape="197.57,518.66 207.61,514.42 207.24,512.17 207.56,511.20 208.21,510.33 209.19,509.57 210.51,508.91 207.29,501.04 205.05,501.46 204.10,501.22 203.26,500.69 202.54,499.86 201.93,498.74 193.12,502.55 193.37,504.86 192.89,505.91 192.00,506.89 190.70,507.80 189.00,508.64 192.30,516.47 194.52,516.02 195.46,516.24 196.28,516.75 196.98,517.56">
        <request index="0" response="000010000" foes="010010000" cont="0"/>
        <request index="1" response="000110000" foes="110110000" cont="0"/>
        <request index="2" response="001001000" foes="001001000" cont="1"/>
        <request index="3" response="000000000" foes="001000100" cont="0"/>
        <request index="4" response="010000000" foes="011000011" cont="0"/>
        <request index="5" response="010000000" foes="111000010" cont="0"/>
        <request index="6" response="000111000" foes="000111100" cont="0"/>
        <request index="7" response="000110011" foes="000110011" cont="1"/>
        <request index="8" response="000100010" foes="000100010" cont="1"/>
    </junction>
    <junction id="345553456" type="traffic_light" x="48.97" y="161.22" incLanes="-40317922#2_0 27222779#0_0 134941607#0_0" intLanes=":345553456_0_0 :345553456_9_0 :345553456_10_0 :345553456_3_0 :345553456_4_0 :345553456_11_0 :345553456_6_0 :345553456_7_0 :345553456_8_0" shape="48.26,167.66 54.14,165.12 53.67,162.91 53.87,161.98 54.37,161.17 55.16,160.48 56.24,159.90 55.00,156.95 52.75,157.40 51.79,157.19 50.95,156.67 50.23,155.87 49.62,154.76 43.76,157.35 44.25,159.56 44.05,160.48 43.56,161.30 42.78,161.99 41.70,162.57 42.95,165.52 45.19,165.06 46.13,165.26 46.96,165.77 47.67,166.57">
        <request index="0" response="111000000" foes="111100000" cont="0"/>
        <request index="1" response="110011000" foes="110011000" cont="1"/>
        <request index="2" response="100010000" foes="100010000" cont="1"/>
        <request index="3" response="010000000" foes="010000010" cont="0"/>
        <request index="4" response="110000000" foes="110000110" cont="0"/>
        <request index="5" response="001000001" foes="001000001" cont="1"/>
        <request index="6" response="000000000" foes="000100001" cont="0"/>
        <request index="7" response="000000010" foes="000011011" cont="0"/>
        <request index="8" response="000000010" foes="000010111" cont="0"/>
    </junction>
    <junction id="618163560" type="priority" x="288.05" y="472.52" incLanes="149935566#0_0 149935566#0_1" intLanes=":618163560_0_0 :618163560_0_1" shape="290.72,474.84 288.11,468.99 286.99,469.20 286.13,469.02 285.63,469.03 285.00,469.21 288.36,477.02 289.30,476.32 289.78,475.55 290.14,475.18">
        <request index="0" response="00" foes="00" cont="0"/>
        <request index="1" response="00" foes="00" cont="0"/>
    </junction>
    <junction id="618697472" type="priority" x="493.89" y="411.61" incLanes="51508352#0_0" intLanes=":618697472_0_0" shape="493.89,411.61 496.81,410.30 493.89,411.61">
        <request index="0" response="0" foes="0" cont="0"/>
    </junction>
    <junction id="8736309647" type="priority" x="180.54" y="465.35" incLanes="-943542797#1_0 392103887_0" intLanes=":8736309647_0_0 :8736309647_1_0 :8736309647_1_1" shape="179.19,470.29 188.00,466.48 186.04,464.03 183.85,462.86 182.82,461.96 181.89,460.41 176.01,462.95">
        <request index="0" response="000" foes="000" cont="0"/>
        <request index="1" response="000" foes="000" cont="0"/>
        <request index="2" response="000" foes="000" cont="0"/>
    </junction>
    <junction id="8748721326" type="dead_end" x="506.82" y="378.74" incLanes="" intLanes="" shape="506.19,377.26 507.44,380.21"/>
    <junction id="8748721381" type="dead_end" x="401.43" y="12.26" incLanes="362368395#0_0 362368395#0_1" intLanes="" shape="400.17,9.32 402.68,15.21"/>
    <junction id="8748896839" type="priority" x="203.28" y="518.18" incLanes="40317921_0" intLanes=":8748896839_0_0" shape="203.28,518.18 208.30,516.05 203.28,518.18">
        <request index="0" response="0" foes="0" cont="0"/>
    </junction>
    <junction id="9094806366" type="dead_end" x="0.00" y="182.06" incLanes="" intLanes="" shape="0.63,183.53 -0.63,180.59"/>
    <junction id="9201837231" type="dead_end" x="23.97" y="356.40" incLanes="4645392#0_0" intLanes="" shape="25.36,359.66 22.57,353.13"/>
    <junction id="967091764" type="traffic_light" x="483.62" y="388.50" incLanes="-51508352#1_0 376401312#0_0 51476080#0_0" intLanes=":967091764_0_0 :967091764_1_0 :967091764_10_0 :967091764_3_0 :967091764_4_0 :967091764_4_1 :967091764_6_0 :967091764_7_0 :967091764_11_0 :967091764_12_0" shape="483.58,396.33 489.43,393.74 488.61,390.78 488.69,389.59 489.10,388.59 489.84,387.78 490.90,387.17 489.66,384.22 487.37,384.52 486.35,384.11 485.43,383.33 484.59,382.17 483.84,380.65 477.93,383.08 478.36,385.31 478.15,386.25 477.64,387.06 476.85,387.76 475.76,388.34 478.25,394.23 480.49,393.77 481.44,393.98 482.27,394.47 482.98,395.25">
        <request index="0" response="0000000000" foes="0000110000" cont="0"/>
        <request index="1" response="0000000000" foes="1101110000" cont="0"/>
        <request index="2" response="0010001000" foes="0010001000" cont="1"/>
        <request index="3" response="0010000000" foes="0010000100" cont="0"/>
        <request index="4" response="0110000011" foes="0110000011" cont="0"/>
        <request index="5" response="0110000011" foes="0110000011" cont="0"/>
        <request index="6" response="0110000010" foes="1110000010" cont="0"/>
        <request index="7" response="0000000000" foes="0001111100" cont="0"/>
        <request index="8" response="0000000010" foes="0001110010" cont="1"/>
        <request index="9" response="0001000010" foes="0001000010" cont="1"/>
    </junction>

    <junction id=":21457468_6_0" type="internal" x="117.95" y="323.20" incLanes=":21457468_2_0 40317922#0_0" intLanes=":21457468_3_0"/>
    <junction id=":21457468_7_0" type="internal" x="115.51" y="313.20" incLanes=":21457468_4_0 -40317922#4_0" intLanes=":21457468_0_0 :21457468_1_0"/>
    <junction id=":21457468_8_0" type="internal" x="114.48" y="311.29" incLanes=":21457468_5_0 -40317922#4_0" intLanes=":21457468_1_0"/>
    <junction id=":29564155_10_0" type="internal" x="335.53" y="45.33" incLanes=":29564155_1_0 344664988#0_0" intLanes=":29564155_3_0 :29564155_4_0 :29564155_7_0 :29564155_7_1 :29564155_9_0"/>
    <junction id=":29564155_11_0" type="internal" x="336.23" y="46.49" incLanes=":29564155_2_0 344664988#0_0 943540702#0_1" intLanes=":29564155_4_0 :29564155_9_0"/>
    <junction id=":29564155_12_0" type="internal" x="332.96" y="34.84" incLanes=":29564155_5_0 -51476080#7_0 943540702#0_0" intLanes=":29564155_0_0 :29564155_6_0"/>
    <junction id=":345553442_9_0" type="internal" x="201.03" y="514.62" incLanes=":345553442_2_0 58561799#0_0 943542797#0_0" intLanes=":345553442_3_0 :345553442_6_0"/>
    <junction id=":345553442_10_0" type="internal" x="198.26" y="504.53" incLanes=":345553442_7_0 -40317921_0" intLanes=":345553442_0_0 :345553442_1_0 :345553442_4_0 :345553442_5_0"/>
    <junction id=":345553442_11_0" type="internal" x="197.27" y="502.07" incLanes=":345553442_8_0 -40317921_0 58561799#0_1" intLanes=":345553442_1_0 :345553442_5_0"/>
    <junction id=":345553456_9_0" type="internal" x="49.26" y="164.54" incLanes=":345553456_1_0 27222779#0_0" intLanes=":345553456_3_0 :345553456_4_0 :345553456_7_0 :345553456_8_0"/>
    <junction id=":345553456_10_0" type="internal" x="49.99" y="165.60" incLanes=":345553456_2_0 134941607#0_0 27222779#0_0" intLanes=":345553456_4_0 :345553456_8_0"/>
    <junction id=":345553456_11_0" type="internal" x="47.91" y="156.83" incLanes=":345553456_5_0 -40317922#2_0 134941607#0_0" intLanes=":345553456_0_0 :345553456_6_0"/>
    <junction id=":967091764_10_0" type="internal" x="485.29" y="394.26" incLanes=":967091764_2_0 376401312#0_0 51476080#0_0" intLanes=":967091764_3_0 :967091764_7_0"/>
    <junction id=":967091764_11_0" type="internal" x="482.78" y="383.72" incLanes=":967091764_8_0 -51508352#1_0" intLanes=":967091764_0_0 :967091764_1_0 :967091764_4_0 :967091764_4_1 :967091764_6_0"/>
    <junction id=":967091764_12_0" type="internal" x="482.08" y="382.67" incLanes=":967091764_9_0 -51508352#1_0 376401312#0_0" intLanes=":967091764_1_0 :967091764_6_0"/>

    <connection from="-27222779#2" to="27222779#0" fromLane="0" toLane="0" via=":2269137859_0_0" dir="t" state="M"/>
    <connection from="-344664988#1" to="344664988#0" fromLane="0" toLane="0" via=":2064183917_0_0" dir="t" state="M"/>
    <connection from="-392103887" to="-40317922#4" fromLane="0" toLane="0" via=":1680609182_0_0" dir="s" state="M"/>
    <connection from="-40317921" to="147557400#0" fromLane="0" toLane="0" via=":345553442_0_0" tl="345553442" linkIndex="0" dir="r" state="o"/>
    <connection from="-40317921" to="-943542797#1" fromLane="0" toLane="0" via=":345553442_1_0" tl="345553442" linkIndex="1" dir="s" state="o"/>
    <connection from="-40317921" to="40317921" fromLane="0" toLane="0" via=":345553442_2_0" tl="345553442" linkIndex="2" dir="t" state="o"/>
    <connection from="-40317922#2" to="-27222779#2" fromLane="0" toLane="0" via=":345553456_0_0" tl="345553456" linkIndex="0" dir="s" state="o"/>
    <connection from="-40317922#2" to="40317927#0" fromLane="0" toLane="0" via=":345553456_1_0" tl="345553456" linkIndex="1" dir="l" state="o"/>
    <connection from="-40317922#2" to="40317922#0" fromLane="0" toLane="0" via=":345553456_2_0" tl="345553456" linkIndex="2" dir="t" state="o"/>
    <connection from="-40317922#4" to="4645392#0" fromLane="0" toLane="0" via=":21457468_0_0" dir="r" state="M"/>
    <connection from="-40317922#4" to="-40317922#2" fromLane="0" toLane="0" via=":21457468_1_0" dir="s" state="M"/>
    <connection from="-40317922#4" to="40317922#3" fromLane="0" toLane="0" via=":21457468_2_0" dir="t" state="m"/>
    <connection from="-51476080#7" to="-344664988#1" fromLane="0" toLane="0" via=":29564155_0_0" tl="29564155" linkIndex="0" dir="s" state="o"/>
    <connection from="-51476080#7" to="362368395#0" fromLane="0" toLane="1" via=":29564155_1_0" tl="29564155" linkIndex="1" dir="l" state="o"/>
    <connection from="-51476080#7" to="51476080#0" fromLane="0" toLane="0" via=":29564155_2_0" tl="29564155" linkIndex="2" dir="t" state="o"/>
    <connection from="-51508352#1" to="149935566#0" fromLane="0" toLane="0" via=":967091764_0_0" tl="967091764" linkIndex="0" dir="r" state="O"/>
    <connection from="-51508352#1" to="-51476080#7" fromLane="0" toLane="0" via=":967091764_1_0" tl="967091764" linkIndex="1" dir="s" state="O"/>
    <connection from="-51508352#1" to="51508352#0" fromLane="0" toLane="0" via=":967091764_2_0" tl="967091764" linkIndex="2" dir="t" state="o"/>
    <connection from="-943542797#1" to="-392103887" fromLane="0" toLane="0" via=":8736309647_0_0" dir="s" state="M"/>
    <connection from="134941607#0" to="-27222779#2" fromLane="0" toLane="0" via=":345553456_6_0" tl="345553456" linkIndex="6" dir="r" state="O"/>
    <connection from="134941607#0" to="40317927#0" fromLane="0" toLane="0" via=":345553456_7_0" tl="345553456" linkIndex="7" dir="s" state="O"/>
    <connection from="134941607#0" to="40317922#0" fromLane="0" toLane="0" via=":345553456_8_0" tl="345553456" linkIndex="8" dir="l" state="O"/>
    <connection from="149935566#0" to="58561799#0" fromLane="0" toLane="0" via=":618163560_0_0" dir="s" state="M"/>
    <connection from="149935566#0" to="58561799#0" fromLane="1" toLane="1" via=":618163560_0_1" dir="s" state="M"/>
    <connection from="27222779#0" to="40317927#0" fromLane="0" toLane="0" via=":345553456_3_0" tl="345553456" linkIndex="3" dir="r" state="o"/>
    <connection from="27222779#0" to="40317922#0" fromLane="0" toLane="0" via=":345553456_4_0" tl="345553456" linkIndex="4" dir="s" state="o"/>
    <connection from="27222779#0" to="-27222779#2" fromLane="0" toLane="0" via=":345553456_5_0" tl="345553456" linkIndex="5" dir="t" state="o"/>
    <connection from="344664988#0" to="362368395#0" fromLane="0" toLane="0" via=":29564155_3_0" tl="29564155" linkIndex="3" dir="r" state="o"/>
    <connection from="344664988#0" to="51476080#0" fromLane="0" toLane="0" via=":29564155_4_0" tl="29564155" linkIndex="4" dir="s" state="o"/>
    <connection from="344664988#0" to="-344664988#1" fromLane="0" toLane="0" via=":29564155_5_0" tl="29564155" linkIndex="5" dir="t" state="o"/>
    <connection from="376401312#0" to="51508352#0" fromLane="0" toLane="0" via=":967091764_3_0" tl="967091764" linkIndex="3" dir="r" state="o"/>
    <connection from="376401312#0" to="149935566#0" fromLane="0" toLane="0" via=":967091764_4_0" tl="967091764" linkIndex="4" dir="s" state="o"/>
    <connection from="376401312#0" to="149935566#0" fromLane="0" toLane="1" via=":967091764_4_1" tl="967091764" linkIndex="5" dir="s" state="o"/>
    <connection from="376401312#0" to="-51476080#7" fromLane="0" toLane="0" via=":967091764_6_0" tl="967091764" linkIndex="6" dir="l" state="o"/>
    <connection from="392103887" to="943542797#0" fromLane="0" toLane="0" via=":8736309647_1_0" dir="s" state="M"/>
    <connection from="392103887" to="943542797#0" fromLane="0" toLane="1" via=":8736309647_1_1" dir="s" state="M"/>
    <connection from="40317921" to="-40317921" fromLane="0" toLane="0" via=":8748896839_0_0" dir="t" state="M"/>
    <connection from="40317922#0" to="40317922#3" fromLane="0" toLane="0" via=":21457468_3_0" dir="s" state="M"/>
    <connection from="40317922#0" to="4645392#0" fromLane="0" toLane="0" via=":21457468_4_0" dir="l" state="m"/>
    <connection from="40317922#0" to="-40317922#2" fromLane="0" toLane="0" via=":21457468_5_0" dir="t" state="m"/>
    <connection from="40317922#3" to="392103887" fromLane="0" toLane="0" via=":1680609182_1_0" dir="s" state="M"/>
    <connection from="40317927#0" to="943540702#0" fromLane="0" toLane="0" via=":2959331869_0_0" dir="s" state="M"/>
    <connection from="40317927#0" to="943540702#0" fromLane="0" toLane="1" via=":2959331869_0_1" dir="s" state="M"/>
    <connection from="51476080#0" to="51508352#0" fromLane="0" toLane="0" via=":967091764_7_0" tl="967091764" linkIndex="7" dir="s" state="O"/>
    <connection from="51476080#0" to="149935566#0" fromLane="0" toLane="1" via=":967091764_8_0" tl="967091764" linkIndex="8" dir="l" state="o"/>
    <connection from="51476080#0" to="-51476080#7" fromLane="0" toLane="0" via=":967091764_9_0" tl="967091764" linkIndex="9" dir="t" state="o"/>
    <connection from="51508352#0" to="-51508352#1" fromLane="0" toLane="0" via=":618697472_0_0" dir="t" state="M"/>
    <connection from="58561799#0" to="40317921" fromLane="0" toLane="0" via=":345553442_3_0" tl="345553442" linkIndex="3" dir="r" state="O"/>
    <connection from="58561799#0" to="147557400#0" fromLane="0" toLane="0" via=":345553442_4_0" tl="345553442" linkIndex="4" dir="s" state="O"/>
    <connection from="58561799#0" to="-943542797#1" fromLane="1" toLane="0" via=":345553442_5_0" tl="345553442" linkIndex="5" dir="l" state="O"/>
    <connection from="943540702#0" to="-344664988#1" fromLane="0" toLane="0" via=":29564155_6_0" tl="29564155" linkIndex="6" dir="r" state="O"/>
    <connection from="943540702#0" to="362368395#0" fromLane="0" toLane="0" via=":29564155_7_0" tl="29564155" linkIndex="7" dir="s" state="O"/>
    <connection from="943540702#0" to="362368395#0" fromLane="1" toLane="1" via=":29564155_7_1" tl="29564155" linkIndex="8" dir="s" state="O"/>
    <connection from="943540702#0" to="51476080#0" fromLane="1" toLane="0" via=":29564155_9_0" tl="29564155" linkIndex="9" dir="l" state="O"/>
    <connection from="943542797#0" to="40317921" fromLane="0" toLane="0" via=":345553442_6_0" tl="345553442" linkIndex="6" dir="s" state="o"/>
    <connection from="943542797#0" to="147557400#0" fromLane="1" toLane="0" via=":345553442_7_0" tl="345553442" linkIndex="7" dir="l" state="o"/>
    <connection from="943542797#0" to="-943542797#1" fromLane="1" toLane="0" via=":345553442_8_0" tl="345553442" linkIndex="8" dir="t" state="o"/>

    <connection from=":1680609182_0" to="-40317922#4" fromLane="0" toLane="0" dir="s" state="M"/>
    <connection from=":1680609182_1" to="392103887" fromLane="0" toLane="0" dir="s" state="M"/>
    <connection from=":2064183917_0" to="344664988#0" fromLane="0" toLane="0" dir="t" state="M"/>
    <connection from=":21457468_0" to="4645392#0" fromLane="0" toLane="0" dir="r" state="M"/>
    <connection from=":21457468_1" to="-40317922#2" fromLane="0" toLane="0" dir="s" state="M"/>
    <connection from=":21457468_2" to="40317922#3" fromLane="0" toLane="0" via=":21457468_6_0" dir="t" state="m"/>
    <connection from=":21457468_6" to="40317922#3" fromLane="0" toLane="0" dir="t" state="M"/>
    <connection from=":21457468_3" to="40317922#3" fromLane="0" toLane="0" dir="s" state="M"/>
    <connection from=":21457468_4" to="4645392#0" fromLane="0" toLane="0" via=":21457468_7_0" dir="l" state="m"/>
    <connection from=":21457468_7" to="4645392#0" fromLane="0" toLane="0" dir="l" state="M"/>
    <connection from=":21457468_5" to="-40317922#2" fromLane="0" toLane="0" via=":21457468_8_0" dir="t" state="m"/>
    <connection from=":21457468_8" to="-40317922#2" fromLane="0" toLane="0" dir="t" state="M"/>
    <connection from=":2269137859_0" to="27222779#0" fromLane="0" toLane="0" dir="t" state="M"/>
    <connection from=":29564155_0" to="-344664988#1" fromLane="0" toLane="0" dir="s" state="M"/>
    <connection from=":29564155_1" to="362368395#0" fromLane="0" toLane="1" via=":29564155_10_0" dir="l" state="m"/>
    <connection from=":29564155_10" to="362368395#0" fromLane="0" toLane="1" dir="l" state="M"/>
    <connection from=":29564155_2" to="51476080#0" fromLane="0" toLane="0" via=":29564155_11_0" dir="t" state="m"/>
    <connection from=":29564155_11" to="51476080#0" fromLane="0" toLane="0" dir="t" state="M"/>
    <connection from=":29564155_3" to="362368395#0" fromLane="0" toLane="0" dir="r" state="M"/>
    <connection from=":29564155_4" to="51476080#0" fromLane="0" toLane="0" dir="s" state="M"/>
    <connection from=":29564155_5" to="-344664988#1" fromLane="0" toLane="0" via=":29564155_12_0" dir="t" state="m"/>
    <connection from=":29564155_12" to="-344664988#1" fromLane="0" toLane="0" dir="t" state="M"/>
    <connection from=":29564155_6" to="-344664988#1" fromLane="0" toLane="0" dir="r" state="M"/>
    <connection from=":29564155_7" to="362368395#0" fromLane="0" toLane="0" dir="s" state="M"/>
    <connection from=":29564155_7" to="362368395#0" fromLane="1" toLane="1" dir="s" state="M"/>
    <connection from=":29564155_9" to="51476080#0" fromLane="0" toLane="0" dir="l" state="M"/>
    <connection from=":2959331869_0" to="943540702#0" fromLane="0" toLane="0" dir="s" state="M"/>
    <connection from=":2959331869_0" to="943540702#0" fromLane="1" toLane="1" dir="s" state="M"/>
    <connection from=":345553442_0" to="147557400#0" fromLane="0" toLane="0" dir="r" state="M"/>
    <connection from=":345553442_1" to="-943542797#1" fromLane="0" toLane="0" dir="s" state="M"/>
    <connection from=":345553442_2" to="40317921" fromLane="0" toLane="0" via=":345553442_9_0" dir="t" state="m"/>
    <connection from=":345553442_9" to="40317921" fromLane="0" toLane="0" dir="t" state="M"/>
    <connection from=":345553442_3" to="40317921" fromLane="0" toLane="0" dir="r" state="M"/>
    <connection from=":345553442_4" to="147557400#0" fromLane="0" toLane="0" dir="s" state="M"/>
    <connection from=":345553442_5" to="-943542797#1" fromLane="0" toLane="0" dir="l" state="M"/>
    <connection from=":345553442_6" to="40317921" fromLane="0" toLane="0" dir="s" state="M"/>
    <connection from=":345553442_7" to="147557400#0" fromLane="0" toLane="0" via=":345553442_10_0" dir="l" state="m"/>
    <connection from=":345553442_10" to="147557400#0" fromLane="0" toLane="0" dir="l" state="M"/>
    <connection from=":345553442_8" to="-943542797#1" fromLane="0" toLane="0" via=":345553442_11_0" dir="t" state="m"/>
    <connection from=":345553442_11" to="-943542797#1" fromLane="0" toLane="0" dir="t" state="M"/>
    <connection from=":345553456_0" to="-27222779#2" fromLane="0" toLane="0" dir="s" state="M"/>
    <connection from=":345553456_1" to="40317927#0" fromLane="0" toLane="0" via=":345553456_9_0" dir="l" state="m"/>
    <connection from=":345553456_9" to="40317927#0" fromLane="0" toLane="0" dir="l" state="M"/>
    <connection from=":345553456_2" to="40317922#0" fromLane="0" toLane="0" via=":345553456_10_0" dir="t" state="m"/>
    <connection from=":345553456_10" to="40317922#0" fromLane="0" toLane="0" dir="t" state="M"/>
    <connection from=":345553456_3" to="40317927#0" fromLane="0" toLane="0" dir="r" state="M"/>
    <connection from=":345553456_4" to="40317922#0" fromLane="0" toLane="0" dir="s" state="M"/>
    <connection from=":345553456_5" to="-27222779#2" fromLane="0" toLane="0" via=":345553456_11_0" dir="t" state="m"/>
    <connection from=":345553456_11" to="-27222779#2" fromLane="0" toLane="0" dir="t" state="M"/>
    <connection from=":345553456_6" to="-27222779#2" fromLane="0" toLane="0" dir="r" state="M"/>
    <connection from=":345553456_7" to="40317927#0" fromLane="0" toLane="0" dir="s" state="M"/>
    <connection from=":345553456_8" to="40317922#0" fromLane="0" toLane="0" dir="l" state="M"/>
    <connection from=":618163560_0" to="58561799#0" fromLane="0" toLane="0" dir="s" state="M"/>
    <connection from=":618163560_0" to="58561799#0" fromLane="1" toLane="1" dir="s" state="M"/>
    <connection from=":618697472_0" to="-51508352#1" fromLane="0" toLane="0" dir="t" state="M"/>
    <connection from=":8736309647_0" to="-392103887" fromLane="0" toLane="0" dir="s" state="M"/>
    <connection from=":8736309647_1" to="943542797#0" fromLane="0" toLane="0" dir="s" state="M"/>
    <connection from=":8736309647_1" to="943542797#0" fromLane="1" toLane="1" dir="s" state="M"/>
    <connection from=":8748896839_0" to="-40317921" fromLane="0" toLane="0" dir="t" state="M"/>
    <connection from=":967091764_0" to="149935566#0" fromLane="0" toLane="0" dir="r" state="M"/>
    <connection from=":967091764_1" to="-51476080#7" fromLane="0" toLane="0" dir="s" state="M"/>
    <connection from=":967091764_2" to="51508352#0" fromLane="0" toLane="0" via=":967091764_10_0" dir="t" state="m"/>
    <connection from=":967091764_10" to="51508352#0" fromLane="0" toLane="0" dir="t" state="M"/>
    <connection from=":967091764_3" to="51508352#0" fromLane="0" toLane="0" dir="r" state="M"/>
    <connection from=":967091764_4" to="149935566#0" fromLane="0" toLane="0" dir="s" state="M"/>
    <connection from=":967091764_4" to="149935566#0" fromLane="1" toLane="1" dir="s" state="M"/>
    <connection from=":967091764_6" to="-51476080#7" fromLane="0" toLane="0" dir="l" state="M"/>
    <connection from=":967091764_7" to="51508352#0" fromLane="0" toLane="0" dir="s" state="M"/>
    <connection from=":967091764_8" to="149935566#0" fromLane="0" toLane="1" via=":967091764_11_0" dir="l" state="m"/>
    <connection from=":967091764_11" to="149935566#0" fromLane="0" toLane="1" dir="l" state="M"/>
    <connection from=":967091764_9" to="-51476080#7" fromLane="0" toLane="0" via=":967091764_12_0" dir="t" state="m"/>
    <connection from=":967091764_12" to="-51476080#7" fromLane="0" toLane="0" dir="t" state="M"/>

</net>
